chitra/__about__.py
chitra/__init__.py
chitra/constants.py
chitra/coordinates.py
chitra/core.py
chitra/datagenerator.py
chitra/dataloader.py
chitra/import_utils.py
chitra/imports.py
chitra/logging.py
chitra/trainer.py
chitra/assets/API.Dockerfile
chitra/cli/__init__.py
chitra/cli/builder.py
chitra/cli/main.py
chitra/data_processing/__init__.py
chitra/data_processing/processor.py
chitra/data_processing/default/__init__.py
chitra/data_processing/default/nlp.py
chitra/data_processing/default/vision.py
chitra/image/__init__.py
chitra/image/image.py
chitra/image/tf_image.py
chitra/serve/__init__.py
chitra/serve/api.py
chitra/serve/app.py
chitra/serve/base.py
chitra/serve/constants.py
chitra/serve/cloud/__init__.py
chitra/serve/cloud/aws_serverless.py
chitra/serve/cloud/base.py
chitra/serve/schema/__init__.py
chitra/serve/schema/text_models.py
chitra/serve/tf_serving/__init__.py
chitra/serve/tf_serving/client.py
chitra/serve/torchserve/__init__.py
chitra/utility/__init__.py
chitra/utility/tf_utils.py
chitra/visualization/__init__.py
chitra/visualization/metrics.py
chitra-0.2.0.dist-info/entry_points.txt
chitra-0.2.0.dist-info/LICENSE
chitra-0.2.0.dist-info/WHEEL
chitra-0.2.0.dist-info/METADATA
chitra-0.2.0.dist-info/RECORD
