Metadata-Version: 2.1
Name: chitra
Version: 0.2.0
Summary: A multi functional library for full stack Deep Learning.
Home-page: https://github.com/aniketmaurya/chitra
Author: Aniket Maurya
Author-email: hello@aniketmaurya.com
Requires-Python: >=3.7
Classifier: Topic :: Software Development :: Libraries :: Python Modules
Classifier: Topic :: Software Development :: Libraries
Classifier: Topic :: Software Development
Classifier: License :: OSI Approved :: Apache Software License
Classifier: Intended Audience :: Information Technology
Classifier: Operating System :: OS Independent
Classifier: Typing :: Typed
Classifier: Development Status :: 4 - Beta
Classifier: Intended Audience :: Developers
Classifier: Programming Language :: Python
Classifier: Programming Language :: Python :: 3
Classifier: Programming Language :: Python :: 3 :: Only
Classifier: Programming Language :: Python :: 3.7
Classifier: Programming Language :: Python :: 3.8
Classifier: Programming Language :: Python :: 3.9
Requires-Dist: matplotlib
Requires-Dist: pillow
Requires-Dist: imgaug >=0.4.0
Requires-Dist: typeguard
Requires-Dist: typer
Requires-Dist: scikit-learn ; extra == "nn"
Requires-Dist: tensorflow >= 2.3 ; extra == "nn"
Requires-Dist: tensorflow-addons >=0.13.0 ; extra == "nn"
Requires-Dist: tf-keras-vis >=0.5.3 ; extra == "nn"
Requires-Dist: pytorch-lightning ; extra == "nn"
Requires-Dist: timm ; extra == "nn"
Requires-Dist: fastapi ; extra == "serve"
Requires-Dist: uvicorn ; extra == "serve"
Requires-Dist: pydantic ; extra == "serve"
Requires-Dist: python-multipart ; extra == "serve"
Requires-Dist: gradio >=2.2.2 ; extra == "serve"
Requires-Dist: tensorflow-serving-api ; extra == "serve"
Requires-Dist: chalice ; extra == "serve"
Requires-Dist: smart_open[all] ; extra == "serve"
Requires-Dist: pytest ; extra == "test"
Requires-Dist: pytest-asyncio ; extra == "test"
Requires-Dist: coverage ; extra == "test"
Project-URL: Documentation, https://chitra.readthedocs.io/en/latest
Provides-Extra: nn
Provides-Extra: serve
Provides-Extra: test
